dedupe_copy/__init__.py
dedupe_copy/__main__.py
dedupe_copy/config.py
dedupe_copy/core.py
dedupe_copy/disk_cache_dict.py
dedupe_copy/logging_config.py
dedupe_copy/manifest.py
dedupe_copy/path_rules.py
dedupe_copy/threads.py
dedupe_copy/ui.py
dedupe_copy/utils.py
dedupe_copy/bin/__init__.py
dedupe_copy/bin/dedupecopy_cli.py
dedupe_copy/bin/manifest_explorer_cli.py
dedupe_copy/test/__init__.py
dedupe_copy/test/benchmark_manifest_save.py
dedupe_copy/test/record_disk_cache_dict_performance.py
dedupe_copy/test/record_manifest_save_performance.py
dedupe_copy/test/test_advanced.py
dedupe_copy/test/test_app_utils.py
dedupe_copy/test/test_cli_validation.py
dedupe_copy/test/test_copy.py
dedupe_copy/test/test_copy_deadlock.py
dedupe_copy/test/test_copy_enhanced.py
dedupe_copy/test/test_copy_race_condition.py
dedupe_copy/test/test_core.py
dedupe_copy/test/test_core_logic.py
dedupe_copy/test/test_delete.py
dedupe_copy/test/test_disk_cache_dict.py
dedupe_copy/test/test_e2e_scenarios.py
dedupe_copy/test/test_golden_dir.py
dedupe_copy/test/test_hashing.py
dedupe_copy/test/test_logging_config.py
dedupe_copy/test/test_main.py
dedupe_copy/test/test_manifest_explorer.py
dedupe_copy/test/test_manifest_memory.py
dedupe_copy/test/test_manifest_performance.py
dedupe_copy/test/test_manifest_resource_leak.py
dedupe_copy/test/test_manifest_rules.py
dedupe_copy/test/test_manifests.py
dedupe_copy/test/test_no_walk.py
dedupe_copy/test/test_reuse_manifest.py
dedupe_copy/test/test_threads.py
dedupe_copy/test/test_user_scenarios.py
dedupe_copy/test/test_verify.py
dedupe_copy/test/test_walk_race_condition.py
dedupe_copy/test/utils.py
dedupecopy-1.2.1.dist-info/licenses/LICENSE
dedupecopy-1.2.1.dist-info/METADATA
dedupecopy-1.2.1.dist-info/WHEEL
dedupecopy-1.2.1.dist-info/entry_points.txt
dedupecopy-1.2.1.dist-info/top_level.txt
dedupecopy-1.2.1.dist-info/RECORD
