Metadata-Version: 2.4
Name: DedupeCopy
Version: 1.2.1
Summary: Find duplicates / copy and restructure file layout command-line tool
Author-email: Erik Schweller <othererik@gmail.com>
Maintainer-email: Erik Schweller <othererik@gmail.com>
License: BSD-2-Clause
Project-URL: Homepage, https://pypi.python.org/pypi/DedupeCopy/
Project-URL: Repository, https://www.github.com/othererik/dedupe_copy
Keywords: de-duplication,file management,deduplication,file-copy,backup,cleanup,disk-space,file-organization,command-line,hashing,manifest
Classifier: Development Status :: 5 - Production/Stable
Classifier: Environment :: Console
Classifier: Intended Audience :: End Users/Desktop
Classifier: Intended Audience :: Developers
Classifier: Programming Language :: Python :: 3
Classifier: Programming Language :: Python :: 3.11
Classifier: Programming Language :: Python :: 3.12
Classifier: Programming Language :: Python :: 3.13
Classifier: Programming Language :: Python :: 3.14
Classifier: License :: OSI Approved :: BSD License
Classifier: Operating System :: OS Independent
Classifier: Topic :: Utilities
Classifier: Topic :: System :: Filesystems
Requires-Python: >=3.11
License-File: LICENSE
Requires-Dist: rich>=13.0.0
Provides-Extra: color
Requires-Dist: colorama>=0.4.0; extra == "color"
Provides-Extra: fast-hash
Requires-Dist: xxhash>=3.4.1; extra == "fast-hash"
Provides-Extra: plot
Requires-Dist: pandas; extra == "plot"
Requires-Dist: matplotlib; extra == "plot"
Dynamic: license-file
